{
  "protectedResources": {
    "users": [
      "GET",
      "POST",
      "PUT",
      "PATCH",
      "DELETE"
    ],
    "XeTrongXuong": [
      "POST",
      "PUT",
      "PATCH",
      "DELETE"
    ]
  },
  "users": [
    {
      "id": 1,
      "firstName": "Administrator",
      "lastName": "",
      "username": "admin",
      "email": "admin@gmail.com",
      "password": "admin",
      "avatar": "https://robohash.org/eaquequasincidunt.png?size=50x50&set=set1",
      "gender": "Genderfluid",
      "phone": "933-658-1213",
      "birthday": "1994-03-23",
      "status": true,
      "createdAt": 1609483221000,
      "modifiedAt": 1609483221000
    }
  ],
  "XeTrongXuong": [
    {
      "id": 1,
      "name": "Pork Salted Bellies",
      "price": 442,
      "quantity": 16,
      "thumbnail": "http://dummyimage.com/213x100.png/dddddd/000000",
      "status": true,
      "createdAt": 1610632995000,
      "modifiedAt": 1615620960000
    }
    
    
  ]
}